{
  "5042002": {
    "chainId": 5042002,
    "chainName": "arc",
    "deployedAt": "2025-12-29T09:32:49.409Z",
    "contracts": {
      "USDC": {
        "address": "0x3600000000000000000000000000000000000000",
        "decimals": 6,
        "name": "USDC",
        "symbol": "USDC"
      },
      "BondFactory": {
        "address": "0x4fA228e2eADF00248D770527bfb15c536a8A40bF"
      },
      "pools": {
        "1": {
          "poolId": "1",
          "name": "ArcBond Series 1",
          "symbol": "arcUSDC",
          "bondToken": "0x8BDDff8591AF59CC6539E3ecDB9EE02D13388e89",
          "bondSeries": "0x709F3EE95be6edb7270126021201ff3BF57eBd0A",
          "maturityDate": "1767605588",
          "createdAt": "1767000788",
          "isActive": true
        }
      }
    }
  },
  "abis": {
    "USDC": [
      {
        "anonymous": false,
        "inputs": [
          {
            "indexed": true,
            "internalType": "address",
            "name": "owner",
            "type": "address"
          },
          {
            "indexed": true,
            "internalType": "address",
            "name": "spender",
            "type": "address"
          },
          {
            "indexed": false,
            "internalType": "uint256",
            "name": "value",
            "type": "uint256"
          }
        ],
        "name": "Approval",
        "type": "event"
      },
      {
        "anonymous": false,
        "inputs": [
          {
            "indexed": true,
            "internalType": "address",
            "name": "from",
            "type": "address"
          },
          {
            "indexed": true,
            "internalType": "address",
            "name": "to",
            "type": "address"
          },
          {
            "indexed": false,
            "internalType": "uint256",
            "name": "value",
            "type": "uint256"
          }
        ],
        "name": "Transfer",
        "type": "event"
      },
      {
        "inputs": [
          {
            "internalType": "address",
            "name": "owner",
            "type": "address"
          },
          {
            "internalType": "address",
            "name": "spender",
            "type": "address"
          }
        ],
        "name": "allowance",
        "outputs": [
          {
            "internalType": "uint256",
            "name": "",
            "type": "uint256"
          }
        ],
        "stateMutability": "view",
        "type": "function"
      },
      {
        "inputs": [
          {
            "internalType": "address",
            "name": "spender",
            "type": "address"
          },
          {
            "internalType": "uint256",
            "name": "amount",
            "type": "uint256"
          }
        ],
        "name": "approve",
        "outputs": [
          {
            "internalType": "bool",
            "name": "",
            "type": "bool"
          }
        ],
        "stateMutability": "nonpayable",
        "type": "function"
      },
      {
        "inputs": [
          {
            "internalType": "address",
            "name": "account",
            "type": "address"
          }
        ],
        "name": "balanceOf",
        "outputs": [
          {
            "internalType": "uint256",
            "name": "",
            "type": "uint256"
          }
        ],
        "stateMutability": "view",
        "type": "function"
      },
      {
        "inputs": [],
        "name": "decimals",
        "outputs": [
          {
            "internalType": "uint8",
            "name": "",
            "type": "uint8"
          }
        ],
        "stateMutability": "view",
        "type": "function"
      },
      {
        "inputs": [],
        "name": "name",
        "outputs": [
          {
            "internalType": "string",
            "name": "",
            "type": "string"
          }
        ],
        "stateMutability": "view",
        "type": "function"
      },
      {
        "inputs": [],
        "name": "symbol",
        "outputs": [
          {
            "internalType": "string",
            "name": "",
            "type": "string"
          }
        ],
        "stateMutability": "view",
        "type": "function"
      },
      {
        "inputs": [],
        "name": "totalSupply",
        "outputs": [
          {
            "internalType": "uint256",
            "name": "",
            "type": "uint256"
          }
        ],
        "stateMutability": "view",
        "type": "function"
      },
      {
        "inputs": [
          {
            "internalType": "address",
            "name": "to",
            "type": "address"
          },
          {
            "internalType": "uint256",
            "name": "amount",
            "type": "uint256"
          }
        ],
        "name": "transfer",
        "outputs": [
          {
            "internalType": "bool",
            "name": "",
            "type": "bool"
          }
        ],
        "stateMutability": "nonpayable",
        "type": "function"
      },
      {
        "inputs": [
          {
            "internalType": "address",
            "name": "from",
            "type": "address"
          },
          {
            "internalType": "address",
            "name": "to",
            "type": "address"
          },
          {
            "internalType": "uint256",
            "name": "amount",
            "type": "uint256"
          }
        ],
        "name": "transferFrom",
        "outputs": [
          {
            "internalType": "bool",
            "name": "",
            "type": "bool"
          }
        ],
        "stateMutability": "nonpayable",
        "type": "function"
      }
    ],
    "BondToken": [
      {
        "inputs": [
          {
            "internalType": "string",
            "name": "name_",
            "type": "string"
          },
          {
            "internalType": "string",
            "name": "symbol_",
            "type": "string"
          },
          {
            "internalType": "address",
            "name": "bondSeries_",
            "type": "address"
          }
        ],
        "stateMutability": "nonpayable",
        "type": "constructor"
      },
      {
        "inputs": [
          {
            "internalType": "address",
            "name": "spender",
            "type": "address"
          },
          {
            "internalType": "uint256",
            "name": "allowance",
            "type": "uint256"
          },
          {
            "internalType": "uint256",
            "name": "needed",
            "type": "uint256"
          }
        ],
        "name": "ERC20InsufficientAllowance",
        "type": "error"
      },
      {
        "inputs": [
          {
            "internalType": "address",
            "name": "sender",
            "type": "address"
          },
          {
            "internalType": "uint256",
            "name": "balance",
            "type": "uint256"
          },
          {
            "internalType": "uint256",
            "name": "needed",
            "type": "uint256"
          }
        ],
        "name": "ERC20InsufficientBalance",
        "type": "error"
      },
      {
        "inputs": [
          {
            "internalType": "address",
            "name": "approver",
            "type": "address"
          }
        ],
        "name": "ERC20InvalidApprover",
        "type": "error"
      },
      {
        "inputs": [
          {
            "internalType": "address",
            "name": "receiver",
            "type": "address"
          }
        ],
        "name": "ERC20InvalidReceiver",
        "type": "error"
      },
      {
        "inputs": [
          {
            "internalType": "address",
            "name": "sender",
            "type": "address"
          }
        ],
        "name": "ERC20InvalidSender",
        "type": "error"
      },
      {
        "inputs": [
          {
            "internalType": "address",
            "name": "spender",
            "type": "address"
          }
        ],
        "name": "ERC20InvalidSpender",
        "type": "error"
      },
      {
        "inputs": [
          {
            "internalType": "address",
            "name": "owner",
            "type": "address"
          }
        ],
        "name": "OwnableInvalidOwner",
        "type": "error"
      },
      {
        "inputs": [
          {
            "internalType": "address",
            "name": "account",
            "type": "address"
          }
        ],
        "name": "OwnableUnauthorizedAccount",
        "type": "error"
      },
      {
        "anonymous": false,
        "inputs": [
          {
            "indexed": true,
            "internalType": "address",
            "name": "owner",
            "type": "address"
          },
          {
            "indexed": true,
            "internalType": "address",
            "name": "spender",
            "type": "address"
          },
          {
            "indexed": false,
            "internalType": "uint256",
            "name": "value",
            "type": "uint256"
          }
        ],
        "name": "Approval",
        "type": "event"
      },
      {
        "anonymous": false,
        "inputs": [
          {
            "indexed": true,
            "internalType": "address",
            "name": "previousOwner",
            "type": "address"
          },
          {
            "indexed": true,
            "internalType": "address",
            "name": "newOwner",
            "type": "address"
          }
        ],
        "name": "OwnershipTransferred",
        "type": "event"
      },
      {
        "anonymous": false,
        "inputs": [
          {
            "indexed": true,
            "internalType": "address",
            "name": "from",
            "type": "address"
          },
          {
            "indexed": true,
            "internalType": "address",
            "name": "to",
            "type": "address"
          },
          {
            "indexed": false,
            "internalType": "uint256",
            "name": "value",
            "type": "uint256"
          }
        ],
        "name": "Transfer",
        "type": "event"
      },
      {
        "inputs": [
          {
            "internalType": "address",
            "name": "owner",
            "type": "address"
          },
          {
            "internalType": "address",
            "name": "spender",
            "type": "address"
          }
        ],
        "name": "allowance",
        "outputs": [
          {
            "internalType": "uint256",
            "name": "",
            "type": "uint256"
          }
        ],
        "stateMutability": "view",
        "type": "function"
      },
      {
        "inputs": [
          {
            "internalType": "address",
            "name": "spender",
            "type": "address"
          },
          {
            "internalType": "uint256",
            "name": "value",
            "type": "uint256"
          }
        ],
        "name": "approve",
        "outputs": [
          {
            "internalType": "bool",
            "name": "",
            "type": "bool"
          }
        ],
        "stateMutability": "nonpayable",
        "type": "function"
      },
      {
        "inputs": [
          {
            "internalType": "address",
            "name": "account",
            "type": "address"
          }
        ],
        "name": "balanceOf",
        "outputs": [
          {
            "internalType": "uint256",
            "name": "",
            "type": "uint256"
          }
        ],
        "stateMutability": "view",
        "type": "function"
      },
      {
        "inputs": [],
        "name": "bondSeries",
        "outputs": [
          {
            "internalType": "address",
            "name": "",
            "type": "address"
          }
        ],
        "stateMutability": "view",
        "type": "function"
      },
      {
        "inputs": [
          {
            "internalType": "address",
            "name": "from",
            "type": "address"
          },
          {
            "internalType": "uint256",
            "name": "amount",
            "type": "uint256"
          }
        ],
        "name": "burn",
        "outputs": [],
        "stateMutability": "nonpayable",
        "type": "function"
      },
      {
        "inputs": [],
        "name": "decimals",
        "outputs": [
          {
            "internalType": "uint8",
            "name": "",
            "type": "uint8"
          }
        ],
        "stateMutability": "pure",
        "type": "function"
      },
      {
        "inputs": [
          {
            "internalType": "address",
            "name": "to",
            "type": "address"
          },
          {
            "internalType": "uint256",
            "name": "amount",
            "type": "uint256"
          }
        ],
        "name": "mint",
        "outputs": [],
        "stateMutability": "nonpayable",
        "type": "function"
      },
      {
        "inputs": [],
        "name": "name",
        "outputs": [
          {
            "internalType": "string",
            "name": "",
            "type": "string"
          }
        ],
        "stateMutability": "view",
        "type": "function"
      },
      {
        "inputs": [],
        "name": "owner",
        "outputs": [
          {
            "internalType": "address",
            "name": "",
            "type": "address"
          }
        ],
        "stateMutability": "view",
        "type": "function"
      },
      {
        "inputs": [],
        "name": "renounceOwnership",
        "outputs": [],
        "stateMutability": "nonpayable",
        "type": "function"
      },
      {
        "inputs": [
          {
            "internalType": "address",
            "name": "bondSeries_",
            "type": "address"
          }
        ],
        "name": "setBondSeries",
        "outputs": [],
        "stateMutability": "nonpayable",
        "type": "function"
      },
      {
        "inputs": [],
        "name": "symbol",
        "outputs": [
          {
            "internalType": "string",
            "name": "",
            "type": "string"
          }
        ],
        "stateMutability": "view",
        "type": "function"
      },
      {
        "inputs": [],
        "name": "totalSupply",
        "outputs": [
          {
            "internalType": "uint256",
            "name": "",
            "type": "uint256"
          }
        ],
        "stateMutability": "view",
        "type": "function"
      },
      {
        "inputs": [
          {
            "internalType": "address",
            "name": "to",
            "type": "address"
          },
          {
            "internalType": "uint256",
            "name": "value",
            "type": "uint256"
          }
        ],
        "name": "transfer",
        "outputs": [
          {
            "internalType": "bool",
            "name": "",
            "type": "bool"
          }
        ],
        "stateMutability": "nonpayable",
        "type": "function"
      },
      {
        "inputs": [
          {
            "internalType": "address",
            "name": "from",
            "type": "address"
          },
          {
            "internalType": "address",
            "name": "to",
            "type": "address"
          },
          {
            "internalType": "uint256",
            "name": "value",
            "type": "uint256"
          }
        ],
        "name": "transferFrom",
        "outputs": [
          {
            "internalType": "bool",
            "name": "",
            "type": "bool"
          }
        ],
        "stateMutability": "nonpayable",
        "type": "function"
      },
      {
        "inputs": [
          {
            "internalType": "address",
            "name": "newOwner",
            "type": "address"
          }
        ],
        "name": "transferOwnership",
        "outputs": [],
        "stateMutability": "nonpayable",
        "type": "function"
      }
    ],
    "BondSeries": [
      {
        "inputs": [
          {
            "internalType": "address",
            "name": "bondToken_",
            "type": "address"
          },
          {
            "internalType": "address",
            "name": "usdc_",
            "type": "address"
          },
          {
            "internalType": "address",
            "name": "keeper_",
            "type": "address"
          },
          {
            "internalType": "uint256",
            "name": "maturityHours_",
            "type": "uint256"
          }
        ],
        "stateMutability": "nonpayable",
        "type": "constructor"
      },
      {
        "inputs": [],
        "name": "AccessControlBadConfirmation",
        "type": "error"
      },
      {
        "inputs": [
          {
            "internalType": "address",
            "name": "account",
            "type": "address"
          },
          {
            "internalType": "bytes32",
            "name": "neededRole",
            "type": "bytes32"
          }
        ],
        "name": "AccessControlUnauthorizedAccount",
        "type": "error"
      },
      {
        "inputs": [],
        "name": "CapExceeded",
        "type": "error"
      },
      {
        "inputs": [],
        "name": "EmergencyNotEnabled",
        "type": "error"
      },
      {
        "inputs": [],
        "name": "EnforcedPause",
        "type": "error"
      },
      {
        "inputs": [],
        "name": "ExpectedPause",
        "type": "error"
      },
      {
        "inputs": [],
        "name": "InsufficientBalance",
        "type": "error"
      },
      {
        "inputs": [],
        "name": "InvalidAmount",
        "type": "error"
      },
      {
        "inputs": [],
        "name": "NotMatured",
        "type": "error"
      },
      {
        "inputs": [],
        "name": "PoolExpired",
        "type": "error"
      },
      {
        "inputs": [],
        "name": "ReentrancyGuardReentrantCall",
        "type": "error"
      },
      {
        "inputs": [],
        "name": "ReserveViolation",
        "type": "error"
      },
      {
        "inputs": [
          {
            "internalType": "address",
            "name": "token",
            "type": "address"
          }
        ],
        "name": "SafeERC20FailedOperation",
        "type": "error"
      },
      {
        "anonymous": false,
        "inputs": [
          {
            "indexed": true,
            "internalType": "address",
            "name": "user",
            "type": "address"
          },
          {
            "indexed": false,
            "internalType": "uint256",
            "name": "usdcAmount",
            "type": "uint256"
          },
          {
            "indexed": false,
            "internalType": "uint256",
            "name": "bondAmount",
            "type": "uint256"
          },
          {
            "indexed": false,
            "internalType": "uint256",
            "name": "timestamp",
            "type": "uint256"
          }
        ],
        "name": "Deposited",
        "type": "event"
      },
      {
        "anonymous": false,
        "inputs": [
          {
            "indexed": false,
            "internalType": "uint256",
            "name": "timestamp",
            "type": "uint256"
          }
        ],
        "name": "EmergencyRedeemEnabled",
        "type": "event"
      },
      {
        "anonymous": false,
        "inputs": [
          {
            "indexed": true,
            "internalType": "address",
            "name": "user",
            "type": "address"
          },
          {
            "indexed": false,
            "internalType": "uint256",
            "name": "amount",
            "type": "uint256"
          },
          {
            "indexed": false,
            "internalType": "uint256",
            "name": "timestamp",
            "type": "uint256"
          }
        ],
        "name": "InterestClaimed",
        "type": "event"
      },
      {
        "anonymous": false,
        "inputs": [
          {
            "indexed": false,
            "internalType": "uint256",
            "name": "amount",
            "type": "uint256"
          },
          {
            "indexed": false,
            "internalType": "uint256",
            "name": "newIndex",
            "type": "uint256"
          },
          {
            "indexed": false,
            "internalType": "uint256",
            "name": "timestamp",
            "type": "uint256"
          }
        ],
        "name": "InterestDistributed",
        "type": "event"
      },
      {
        "anonymous": false,
        "inputs": [
          {
            "indexed": true,
            "internalType": "address",
            "name": "owner",
            "type": "address"
          },
          {
            "indexed": false,
            "internalType": "uint256",
            "name": "amount",
            "type": "uint256"
          },
          {
            "indexed": false,
            "internalType": "uint256",
            "name": "timestamp",
            "type": "uint256"
          }
        ],
        "name": "OwnerWithdraw",
        "type": "event"
      },
      {
        "anonymous": false,
        "inputs": [
          {
            "indexed": false,
            "internalType": "address",
            "name": "account",
            "type": "address"
          }
        ],
        "name": "Paused",
        "type": "event"
      },
      {
        "anonymous": false,
        "inputs": [
          {
            "indexed": true,
            "internalType": "address",
            "name": "user",
            "type": "address"
          },
          {
            "indexed": false,
            "internalType": "uint256",
            "name": "bondAmount",
            "type": "uint256"
          },
          {
            "indexed": false,
            "internalType": "uint256",
            "name": "usdcAmount",
            "type": "uint256"
          },
          {
            "indexed": false,
            "internalType": "uint256",
            "name": "timestamp",
            "type": "uint256"
          }
        ],
        "name": "Redeemed",
        "type": "event"
      },
      {
        "anonymous": false,
        "inputs": [
          {
            "indexed": true,
            "internalType": "bytes32",
            "name": "role",
            "type": "bytes32"
          },
          {
            "indexed": true,
            "internalType": "bytes32",
            "name": "previousAdminRole",
            "type": "bytes32"
          },
          {
            "indexed": true,
            "internalType": "bytes32",
            "name": "newAdminRole",
            "type": "bytes32"
          }
        ],
        "name": "RoleAdminChanged",
        "type": "event"
      },
      {
        "anonymous": false,
        "inputs": [
          {
            "indexed": true,
            "internalType": "bytes32",
            "name": "role",
            "type": "bytes32"
          },
          {
            "indexed": true,
            "internalType": "address",
            "name": "account",
            "type": "address"
          },
          {
            "indexed": true,
            "internalType": "address",
            "name": "sender",
            "type": "address"
          }
        ],
        "name": "RoleGranted",
        "type": "event"
      },
      {
        "anonymous": false,
        "inputs": [
          {
            "indexed": true,
            "internalType": "bytes32",
            "name": "role",
            "type": "bytes32"
          },
          {
            "indexed": true,
            "internalType": "address",
            "name": "account",
            "type": "address"
          },
          {
            "indexed": true,
            "internalType": "address",
            "name": "sender",
            "type": "address"
          }
        ],
        "name": "RoleRevoked",
        "type": "event"
      },
      {
        "anonymous": false,
        "inputs": [
          {
            "indexed": false,
            "internalType": "address",
            "name": "account",
            "type": "address"
          }
        ],
        "name": "Unpaused",
        "type": "event"
      },
      {
        "inputs": [],
        "name": "COUPON_PER_TOKEN_PER_DAY",
        "outputs": [
          {
            "internalType": "uint256",
            "name": "",
            "type": "uint256"
          }
        ],
        "stateMutability": "view",
        "type": "function"
      },
      {
        "inputs": [],
        "name": "COUPON_RATE_PER_DAY",
        "outputs": [
          {
            "internalType": "uint256",
            "name": "",
            "type": "uint256"
          }
        ],
        "stateMutability": "view",
        "type": "function"
      },
      {
        "inputs": [],
        "name": "DEFAULT_ADMIN_ROLE",
        "outputs": [
          {
            "internalType": "bytes32",
            "name": "",
            "type": "bytes32"
          }
        ],
        "stateMutability": "view",
        "type": "function"
      },
      {
        "inputs": [],
        "name": "DEFAULT_GRACE_PERIOD",
        "outputs": [
          {
            "internalType": "uint256",
            "name": "",
            "type": "uint256"
          }
        ],
        "stateMutability": "view",
        "type": "function"
      },
      {
        "inputs": [],
        "name": "FACE_VALUE_PER_TOKEN",
        "outputs": [
          {
            "internalType": "uint256",
            "name": "",
            "type": "uint256"
          }
        ],
        "stateMutability": "view",
        "type": "function"
      },
      {
        "inputs": [],
        "name": "INDEX_RATE_PER_SECOND",
        "outputs": [
          {
            "internalType": "uint256",
            "name": "",
            "type": "uint256"
          }
        ],
        "stateMutability": "view",
        "type": "function"
      },
      {
        "inputs": [],
        "name": "KEEPER_ROLE",
        "outputs": [
          {
            "internalType": "bytes32",
            "name": "",
            "type": "bytes32"
          }
        ],
        "stateMutability": "view",
        "type": "function"
      },
      {
        "inputs": [],
        "name": "MAX_CAP",
        "outputs": [
          {
            "internalType": "uint256",
            "name": "",
            "type": "uint256"
          }
        ],
        "stateMutability": "view",
        "type": "function"
      },
      {
        "inputs": [],
        "name": "MINT_RATIO",
        "outputs": [
          {
            "internalType": "uint256",
            "name": "",
            "type": "uint256"
          }
        ],
        "stateMutability": "view",
        "type": "function"
      },
      {
        "inputs": [],
        "name": "PRECISION",
        "outputs": [
          {
            "internalType": "uint256",
            "name": "",
            "type": "uint256"
          }
        ],
        "stateMutability": "view",
        "type": "function"
      },
      {
        "inputs": [],
        "name": "RESERVE_RATIO",
        "outputs": [
          {
            "internalType": "uint256",
            "name": "",
            "type": "uint256"
          }
        ],
        "stateMutability": "view",
        "type": "function"
      },
      {
        "inputs": [
          {
            "internalType": "address",
            "name": "from",
            "type": "address"
          },
          {
            "internalType": "address",
            "name": "to",
            "type": "address"
          },
          {
            "internalType": "uint256",
            "name": "",
            "type": "uint256"
          }
        ],
        "name": "_handleTransfer",
        "outputs": [],
        "stateMutability": "nonpayable",
        "type": "function"
      },
      {
        "inputs": [],
        "name": "bondToken",
        "outputs": [
          {
            "internalType": "contract BondToken",
            "name": "",
            "type": "address"
          }
        ],
        "stateMutability": "view",
        "type": "function"
      },
      {
        "inputs": [],
        "name": "checkEmergencyMode",
        "outputs": [],
        "stateMutability": "nonpayable",
        "type": "function"
      },
      {
        "inputs": [],
        "name": "claimInterest",
        "outputs": [
          {
            "internalType": "uint256",
            "name": "claimed",
            "type": "uint256"
          }
        ],
        "stateMutability": "nonpayable",
        "type": "function"
      },
      {
        "inputs": [
          {
            "internalType": "address",
            "name": "user",
            "type": "address"
          }
        ],
        "name": "claimableAmount",
        "outputs": [
          {
            "internalType": "uint256",
            "name": "",
            "type": "uint256"
          }
        ],
        "stateMutability": "view",
        "type": "function"
      },
      {
        "inputs": [
          {
            "internalType": "address",
            "name": "",
            "type": "address"
          }
        ],
        "name": "claimedIndex",
        "outputs": [
          {
            "internalType": "uint256",
            "name": "",
            "type": "uint256"
          }
        ],
        "stateMutability": "view",
        "type": "function"
      },
      {
        "inputs": [
          {
            "internalType": "uint256",
            "name": "usdcAmount",
            "type": "uint256"
          }
        ],
        "name": "deposit",
        "outputs": [],
        "stateMutability": "nonpayable",
        "type": "function"
      },
      {
        "inputs": [
          {
            "internalType": "uint256",
            "name": "amount",
            "type": "uint256"
          }
        ],
        "name": "distributeInterest",
        "outputs": [],
        "stateMutability": "nonpayable",
        "type": "function"
      },
      {
        "inputs": [
          {
            "internalType": "uint256",
            "name": "bondAmount",
            "type": "uint256"
          }
        ],
        "name": "emergencyRedeem",
        "outputs": [],
        "stateMutability": "nonpayable",
        "type": "function"
      },
      {
        "inputs": [],
        "name": "emergencyRedeemEnabled",
        "outputs": [
          {
            "internalType": "bool",
            "name": "",
            "type": "bool"
          }
        ],
        "stateMutability": "view",
        "type": "function"
      },
      {
        "inputs": [],
        "name": "getCurrentIndex",
        "outputs": [
          {
            "internalType": "uint256",
            "name": "",
            "type": "uint256"
          }
        ],
        "stateMutability": "view",
        "type": "function"
      },
      {
        "inputs": [
          {
            "internalType": "bytes32",
            "name": "role",
            "type": "bytes32"
          }
        ],
        "name": "getRoleAdmin",
        "outputs": [
          {
            "internalType": "bytes32",
            "name": "",
            "type": "bytes32"
          }
        ],
        "stateMutability": "view",
        "type": "function"
      },
      {
        "inputs": [],
        "name": "getSeriesInfo",
        "outputs": [
          {
            "internalType": "uint256",
            "name": "_maturityDate",
            "type": "uint256"
          },
          {
            "internalType": "uint256",
            "name": "_totalDeposited",
            "type": "uint256"
          },
          {
            "internalType": "uint256",
            "name": "_totalSupply",
            "type": "uint256"
          },
          {
            "internalType": "uint256",
            "name": "_currentIndex",
            "type": "uint256"
          },
          {
            "internalType": "uint256",
            "name": "_lastDistributionTime",
            "type": "uint256"
          },
          {
            "internalType": "bool",
            "name": "_emergencyMode",
            "type": "bool"
          }
        ],
        "stateMutability": "view",
        "type": "function"
      },
      {
        "inputs": [],
        "name": "getTreasuryStatus",
        "outputs": [
          {
            "internalType": "uint256",
            "name": "balance",
            "type": "uint256"
          },
          {
            "internalType": "uint256",
            "name": "required",
            "type": "uint256"
          },
          {
            "internalType": "uint256",
            "name": "withdrawable",
            "type": "uint256"
          }
        ],
        "stateMutability": "view",
        "type": "function"
      },
      {
        "inputs": [
          {
            "internalType": "bytes32",
            "name": "role",
            "type": "bytes32"
          },
          {
            "internalType": "address",
            "name": "account",
            "type": "address"
          }
        ],
        "name": "grantRole",
        "outputs": [],
        "stateMutability": "nonpayable",
        "type": "function"
      },
      {
        "inputs": [
          {
            "internalType": "bytes32",
            "name": "role",
            "type": "bytes32"
          },
          {
            "internalType": "address",
            "name": "account",
            "type": "address"
          }
        ],
        "name": "hasRole",
        "outputs": [
          {
            "internalType": "bool",
            "name": "",
            "type": "bool"
          }
        ],
        "stateMutability": "view",
        "type": "function"
      },
      {
        "inputs": [
          {
            "internalType": "address",
            "name": "",
            "type": "address"
          }
        ],
        "name": "interestReceived",
        "outputs": [
          {
            "internalType": "uint256",
            "name": "",
            "type": "uint256"
          }
        ],
        "stateMutability": "view",
        "type": "function"
      },
      {
        "inputs": [],
        "name": "lastDistributionIndex",
        "outputs": [
          {
            "internalType": "uint256",
            "name": "",
            "type": "uint256"
          }
        ],
        "stateMutability": "view",
        "type": "function"
      },
      {
        "inputs": [],
        "name": "lastDistributionTime",
        "outputs": [
          {
            "internalType": "uint256",
            "name": "",
            "type": "uint256"
          }
        ],
        "stateMutability": "view",
        "type": "function"
      },
      {
        "inputs": [],
        "name": "maturityDate",
        "outputs": [
          {
            "internalType": "uint256",
            "name": "",
            "type": "uint256"
          }
        ],
        "stateMutability": "view",
        "type": "function"
      },
      {
        "inputs": [
          {
            "internalType": "uint256",
            "name": "amount",
            "type": "uint256"
          }
        ],
        "name": "ownerWithdraw",
        "outputs": [],
        "stateMutability": "nonpayable",
        "type": "function"
      },
      {
        "inputs": [],
        "name": "pause",
        "outputs": [],
        "stateMutability": "nonpayable",
        "type": "function"
      },
      {
        "inputs": [],
        "name": "paused",
        "outputs": [
          {
            "internalType": "bool",
            "name": "",
            "type": "bool"
          }
        ],
        "stateMutability": "view",
        "type": "function"
      },
      {
        "inputs": [
          {
            "internalType": "uint256",
            "name": "bondAmount",
            "type": "uint256"
          }
        ],
        "name": "redeem",
        "outputs": [],
        "stateMutability": "nonpayable",
        "type": "function"
      },
      {
        "inputs": [
          {
            "internalType": "bytes32",
            "name": "role",
            "type": "bytes32"
          },
          {
            "internalType": "address",
            "name": "callerConfirmation",
            "type": "address"
          }
        ],
        "name": "renounceRole",
        "outputs": [],
        "stateMutability": "nonpayable",
        "type": "function"
      },
      {
        "inputs": [
          {
            "internalType": "bytes32",
            "name": "role",
            "type": "bytes32"
          },
          {
            "internalType": "address",
            "name": "account",
            "type": "address"
          }
        ],
        "name": "revokeRole",
        "outputs": [],
        "stateMutability": "nonpayable",
        "type": "function"
      },
      {
        "inputs": [
          {
            "internalType": "bytes4",
            "name": "interfaceId",
            "type": "bytes4"
          }
        ],
        "name": "supportsInterface",
        "outputs": [
          {
            "internalType": "bool",
            "name": "",
            "type": "bool"
          }
        ],
        "stateMutability": "view",
        "type": "function"
      },
      {
        "inputs": [],
        "name": "totalDeposited",
        "outputs": [
          {
            "internalType": "uint256",
            "name": "",
            "type": "uint256"
          }
        ],
        "stateMutability": "view",
        "type": "function"
      },
      {
        "inputs": [],
        "name": "unpause",
        "outputs": [],
        "stateMutability": "nonpayable",
        "type": "function"
      },
      {
        "inputs": [],
        "name": "usdc",
        "outputs": [
          {
            "internalType": "contract IERC20",
            "name": "",
            "type": "address"
          }
        ],
        "stateMutability": "view",
        "type": "function"
      }
    ],
    "BondFactory": [
      {
        "inputs": [
          {
            "internalType": "address",
            "name": "usdc_",
            "type": "address"
          },
          {
            "internalType": "address",
            "name": "admin_",
            "type": "address"
          }
        ],
        "stateMutability": "nonpayable",
        "type": "constructor"
      },
      {
        "inputs": [],
        "name": "AccessControlBadConfirmation",
        "type": "error"
      },
      {
        "inputs": [
          {
            "internalType": "address",
            "name": "account",
            "type": "address"
          },
          {
            "internalType": "bytes32",
            "name": "neededRole",
            "type": "bytes32"
          }
        ],
        "name": "AccessControlUnauthorizedAccount",
        "type": "error"
      },
      {
        "inputs": [],
        "name": "InvalidAddress",
        "type": "error"
      },
      {
        "inputs": [],
        "name": "InvalidMaturityHours",
        "type": "error"
      },
      {
        "inputs": [],
        "name": "InvalidName",
        "type": "error"
      },
      {
        "inputs": [],
        "name": "PoolNotFound",
        "type": "error"
      },
      {
        "anonymous": false,
        "inputs": [
          {
            "indexed": true,
            "internalType": "uint256",
            "name": "poolId",
            "type": "uint256"
          },
          {
            "indexed": true,
            "internalType": "address",
            "name": "bondToken",
            "type": "address"
          },
          {
            "indexed": true,
            "internalType": "address",
            "name": "bondSeries",
            "type": "address"
          },
          {
            "indexed": false,
            "internalType": "uint256",
            "name": "maturityDate",
            "type": "uint256"
          },
          {
            "indexed": false,
            "internalType": "string",
            "name": "name",
            "type": "string"
          },
          {
            "indexed": false,
            "internalType": "string",
            "name": "symbol",
            "type": "string"
          }
        ],
        "name": "PoolCreated",
        "type": "event"
      },
      {
        "anonymous": false,
        "inputs": [
          {
            "indexed": true,
            "internalType": "bytes32",
            "name": "role",
            "type": "bytes32"
          },
          {
            "indexed": true,
            "internalType": "bytes32",
            "name": "previousAdminRole",
            "type": "bytes32"
          },
          {
            "indexed": true,
            "internalType": "bytes32",
            "name": "newAdminRole",
            "type": "bytes32"
          }
        ],
        "name": "RoleAdminChanged",
        "type": "event"
      },
      {
        "anonymous": false,
        "inputs": [
          {
            "indexed": true,
            "internalType": "bytes32",
            "name": "role",
            "type": "bytes32"
          },
          {
            "indexed": true,
            "internalType": "address",
            "name": "account",
            "type": "address"
          },
          {
            "indexed": true,
            "internalType": "address",
            "name": "sender",
            "type": "address"
          }
        ],
        "name": "RoleGranted",
        "type": "event"
      },
      {
        "anonymous": false,
        "inputs": [
          {
            "indexed": true,
            "internalType": "bytes32",
            "name": "role",
            "type": "bytes32"
          },
          {
            "indexed": true,
            "internalType": "address",
            "name": "account",
            "type": "address"
          },
          {
            "indexed": true,
            "internalType": "address",
            "name": "sender",
            "type": "address"
          }
        ],
        "name": "RoleRevoked",
        "type": "event"
      },
      {
        "inputs": [],
        "name": "DEFAULT_ADMIN_ROLE",
        "outputs": [
          {
            "internalType": "bytes32",
            "name": "",
            "type": "bytes32"
          }
        ],
        "stateMutability": "view",
        "type": "function"
      },
      {
        "inputs": [],
        "name": "POOL_CREATOR_ROLE",
        "outputs": [
          {
            "internalType": "bytes32",
            "name": "",
            "type": "bytes32"
          }
        ],
        "stateMutability": "view",
        "type": "function"
      },
      {
        "inputs": [
          {
            "internalType": "string",
            "name": "name_",
            "type": "string"
          },
          {
            "internalType": "address",
            "name": "keeper_",
            "type": "address"
          },
          {
            "internalType": "uint256",
            "name": "maturityHours_",
            "type": "uint256"
          }
        ],
        "name": "createPool",
        "outputs": [
          {
            "internalType": "uint256",
            "name": "poolId",
            "type": "uint256"
          },
          {
            "internalType": "address",
            "name": "bondToken",
            "type": "address"
          },
          {
            "internalType": "address",
            "name": "bondSeries",
            "type": "address"
          }
        ],
        "stateMutability": "nonpayable",
        "type": "function"
      },
      {
        "inputs": [
          {
            "internalType": "uint256",
            "name": "poolId",
            "type": "uint256"
          }
        ],
        "name": "deactivatePool",
        "outputs": [],
        "stateMutability": "nonpayable",
        "type": "function"
      },
      {
        "inputs": [],
        "name": "getActivePools",
        "outputs": [
          {
            "components": [
              {
                "internalType": "uint256",
                "name": "poolId",
                "type": "uint256"
              },
              {
                "internalType": "address",
                "name": "bondToken",
                "type": "address"
              },
              {
                "internalType": "address",
                "name": "bondSeries",
                "type": "address"
              },
              {
                "internalType": "uint256",
                "name": "maturityDate",
                "type": "uint256"
              },
              {
                "internalType": "uint256",
                "name": "createdAt",
                "type": "uint256"
              },
              {
                "internalType": "bool",
                "name": "isActive",
                "type": "bool"
              },
              {
                "internalType": "string",
                "name": "name",
                "type": "string"
              },
              {
                "internalType": "string",
                "name": "symbol",
                "type": "string"
              }
            ],
            "internalType": "struct BondFactory.PoolInfo[]",
            "name": "",
            "type": "tuple[]"
          }
        ],
        "stateMutability": "view",
        "type": "function"
      },
      {
        "inputs": [],
        "name": "getAllPools",
        "outputs": [
          {
            "components": [
              {
                "internalType": "uint256",
                "name": "poolId",
                "type": "uint256"
              },
              {
                "internalType": "address",
                "name": "bondToken",
                "type": "address"
              },
              {
                "internalType": "address",
                "name": "bondSeries",
                "type": "address"
              },
              {
                "internalType": "uint256",
                "name": "maturityDate",
                "type": "uint256"
              },
              {
                "internalType": "uint256",
                "name": "createdAt",
                "type": "uint256"
              },
              {
                "internalType": "bool",
                "name": "isActive",
                "type": "bool"
              },
              {
                "internalType": "string",
                "name": "name",
                "type": "string"
              },
              {
                "internalType": "string",
                "name": "symbol",
                "type": "string"
              }
            ],
            "internalType": "struct BondFactory.PoolInfo[]",
            "name": "",
            "type": "tuple[]"
          }
        ],
        "stateMutability": "view",
        "type": "function"
      },
      {
        "inputs": [
          {
            "internalType": "uint256",
            "name": "poolId",
            "type": "uint256"
          }
        ],
        "name": "getPool",
        "outputs": [
          {
            "components": [
              {
                "internalType": "uint256",
                "name": "poolId",
                "type": "uint256"
              },
              {
                "internalType": "address",
                "name": "bondToken",
                "type": "address"
              },
              {
                "internalType": "address",
                "name": "bondSeries",
                "type": "address"
              },
              {
                "internalType": "uint256",
                "name": "maturityDate",
                "type": "uint256"
              },
              {
                "internalType": "uint256",
                "name": "createdAt",
                "type": "uint256"
              },
              {
                "internalType": "bool",
                "name": "isActive",
                "type": "bool"
              },
              {
                "internalType": "string",
                "name": "name",
                "type": "string"
              },
              {
                "internalType": "string",
                "name": "symbol",
                "type": "string"
              }
            ],
            "internalType": "struct BondFactory.PoolInfo",
            "name": "",
            "type": "tuple"
          }
        ],
        "stateMutability": "view",
        "type": "function"
      },
      {
        "inputs": [
          {
            "internalType": "address",
            "name": "bondSeries_",
            "type": "address"
          }
        ],
        "name": "getPoolByBondSeries",
        "outputs": [
          {
            "components": [
              {
                "internalType": "uint256",
                "name": "poolId",
                "type": "uint256"
              },
              {
                "internalType": "address",
                "name": "bondToken",
                "type": "address"
              },
              {
                "internalType": "address",
                "name": "bondSeries",
                "type": "address"
              },
              {
                "internalType": "uint256",
                "name": "maturityDate",
                "type": "uint256"
              },
              {
                "internalType": "uint256",
                "name": "createdAt",
                "type": "uint256"
              },
              {
                "internalType": "bool",
                "name": "isActive",
                "type": "bool"
              },
              {
                "internalType": "string",
                "name": "name",
                "type": "string"
              },
              {
                "internalType": "string",
                "name": "symbol",
                "type": "string"
              }
            ],
            "internalType": "struct BondFactory.PoolInfo",
            "name": "",
            "type": "tuple"
          }
        ],
        "stateMutability": "view",
        "type": "function"
      },
      {
        "inputs": [
          {
            "internalType": "address",
            "name": "bondToken_",
            "type": "address"
          }
        ],
        "name": "getPoolByBondToken",
        "outputs": [
          {
            "components": [
              {
                "internalType": "uint256",
                "name": "poolId",
                "type": "uint256"
              },
              {
                "internalType": "address",
                "name": "bondToken",
                "type": "address"
              },
              {
                "internalType": "address",
                "name": "bondSeries",
                "type": "address"
              },
              {
                "internalType": "uint256",
                "name": "maturityDate",
                "type": "uint256"
              },
              {
                "internalType": "uint256",
                "name": "createdAt",
                "type": "uint256"
              },
              {
                "internalType": "bool",
                "name": "isActive",
                "type": "bool"
              },
              {
                "internalType": "string",
                "name": "name",
                "type": "string"
              },
              {
                "internalType": "string",
                "name": "symbol",
                "type": "string"
              }
            ],
            "internalType": "struct BondFactory.PoolInfo",
            "name": "",
            "type": "tuple"
          }
        ],
        "stateMutability": "view",
        "type": "function"
      },
      {
        "inputs": [],
        "name": "getPoolCount",
        "outputs": [
          {
            "internalType": "uint256",
            "name": "",
            "type": "uint256"
          }
        ],
        "stateMutability": "view",
        "type": "function"
      },
      {
        "inputs": [
          {
            "internalType": "bytes32",
            "name": "role",
            "type": "bytes32"
          }
        ],
        "name": "getRoleAdmin",
        "outputs": [
          {
            "internalType": "bytes32",
            "name": "",
            "type": "bytes32"
          }
        ],
        "stateMutability": "view",
        "type": "function"
      },
      {
        "inputs": [
          {
            "internalType": "address",
            "name": "account",
            "type": "address"
          }
        ],
        "name": "grantPoolCreatorRole",
        "outputs": [],
        "stateMutability": "nonpayable",
        "type": "function"
      },
      {
        "inputs": [
          {
            "internalType": "bytes32",
            "name": "role",
            "type": "bytes32"
          },
          {
            "internalType": "address",
            "name": "account",
            "type": "address"
          }
        ],
        "name": "grantRole",
        "outputs": [],
        "stateMutability": "nonpayable",
        "type": "function"
      },
      {
        "inputs": [
          {
            "internalType": "bytes32",
            "name": "role",
            "type": "bytes32"
          },
          {
            "internalType": "address",
            "name": "account",
            "type": "address"
          }
        ],
        "name": "hasRole",
        "outputs": [
          {
            "internalType": "bool",
            "name": "",
            "type": "bool"
          }
        ],
        "stateMutability": "view",
        "type": "function"
      },
      {
        "inputs": [
          {
            "internalType": "uint256",
            "name": "poolId",
            "type": "uint256"
          }
        ],
        "name": "isPoolActive",
        "outputs": [
          {
            "internalType": "bool",
            "name": "",
            "type": "bool"
          }
        ],
        "stateMutability": "view",
        "type": "function"
      },
      {
        "inputs": [],
        "name": "poolCount",
        "outputs": [
          {
            "internalType": "uint256",
            "name": "",
            "type": "uint256"
          }
        ],
        "stateMutability": "view",
        "type": "function"
      },
      {
        "inputs": [
          {
            "internalType": "address",
            "name": "",
            "type": "address"
          }
        ],
        "name": "poolIdByBondSeries",
        "outputs": [
          {
            "internalType": "uint256",
            "name": "",
            "type": "uint256"
          }
        ],
        "stateMutability": "view",
        "type": "function"
      },
      {
        "inputs": [
          {
            "internalType": "address",
            "name": "",
            "type": "address"
          }
        ],
        "name": "poolIdByBondToken",
        "outputs": [
          {
            "internalType": "uint256",
            "name": "",
            "type": "uint256"
          }
        ],
        "stateMutability": "view",
        "type": "function"
      },
      {
        "inputs": [
          {
            "internalType": "uint256",
            "name": "",
            "type": "uint256"
          }
        ],
        "name": "pools",
        "outputs": [
          {
            "internalType": "uint256",
            "name": "poolId",
            "type": "uint256"
          },
          {
            "internalType": "address",
            "name": "bondToken",
            "type": "address"
          },
          {
            "internalType": "address",
            "name": "bondSeries",
            "type": "address"
          },
          {
            "internalType": "uint256",
            "name": "maturityDate",
            "type": "uint256"
          },
          {
            "internalType": "uint256",
            "name": "createdAt",
            "type": "uint256"
          },
          {
            "internalType": "bool",
            "name": "isActive",
            "type": "bool"
          },
          {
            "internalType": "string",
            "name": "name",
            "type": "string"
          },
          {
            "internalType": "string",
            "name": "symbol",
            "type": "string"
          }
        ],
        "stateMutability": "view",
        "type": "function"
      },
      {
        "inputs": [
          {
            "internalType": "bytes32",
            "name": "role",
            "type": "bytes32"
          },
          {
            "internalType": "address",
            "name": "callerConfirmation",
            "type": "address"
          }
        ],
        "name": "renounceRole",
        "outputs": [],
        "stateMutability": "nonpayable",
        "type": "function"
      },
      {
        "inputs": [
          {
            "internalType": "address",
            "name": "account",
            "type": "address"
          }
        ],
        "name": "revokePoolCreatorRole",
        "outputs": [],
        "stateMutability": "nonpayable",
        "type": "function"
      },
      {
        "inputs": [
          {
            "internalType": "bytes32",
            "name": "role",
            "type": "bytes32"
          },
          {
            "internalType": "address",
            "name": "account",
            "type": "address"
          }
        ],
        "name": "revokeRole",
        "outputs": [],
        "stateMutability": "nonpayable",
        "type": "function"
      },
      {
        "inputs": [
          {
            "internalType": "bytes4",
            "name": "interfaceId",
            "type": "bytes4"
          }
        ],
        "name": "supportsInterface",
        "outputs": [
          {
            "internalType": "bool",
            "name": "",
            "type": "bool"
          }
        ],
        "stateMutability": "view",
        "type": "function"
      },
      {
        "inputs": [],
        "name": "usdc",
        "outputs": [
          {
            "internalType": "address",
            "name": "",
            "type": "address"
          }
        ],
        "stateMutability": "view",
        "type": "function"
      }
    ]
  }
}